<annotation>
	<folder>images</folder>
	<filename>280.jpg</filename>
	<path>/home/dodo/Objetos RoboCup 2018/images/280.jpg</path>
	<source>
		<database>Unknown</database>
	</source>
	<size>
		<width>3474</width>
		<height>4632</height>
		<depth>3</depth>
	</size>
	<segmented>0</segmented>
	<object>
		<name>paprika</name>
		<pose>Unspecified</pose>
		<truncated>0</truncated>
		<difficult>0</difficult>
		<bndbox>
			<xmin>1718</xmin>
			<ymin>1726</ymin>
			<xmax>2790</xmax>
			<ymax>2869</ymax>
		</bndbox>
	</object>
</annotation>
